[
  {
    "raw": "FIT SHPR",
    "web": "Fit Fruit & Vegetable Wash",
    "id": "0082854511012"
  },
  {
    "raw": "HATCH GREEN CHILES",
    "web": "Hatch Farms Fire-Roasted Diced Green Chiles",
    "id": "0002818920466"
  },
  {
    "raw": "OLD EL PASO SEASNG",
    "web": "Old El Paso Original Taco Seasoning Mix",
    "id": "0004600028869"
  },
  {
    "raw": "ST PECAN HLV RAW",
    "web": "Simple Truth™ Pecan Halves",
    "id": "0001111002471"
  },
  {
    "raw": "TACO BELL SEASNING",
    "web": "Taco Bell Original Taco Seasoning Mix",
    "id": "0002100003934"
  }
]
